{
    "folder": "theologie_familiere",
    "offset": 15,
    "min": 125,
    "max": 170,
    "chapters": [
        ["Titre", 125],
        ["Entrée du Prestre à l’Autel", 127],
        ["Le Confiteor", 128],
        ["Deus tu conversus, &c", 129],
        ["L’Introit", 130],
        ["Kyrie eleison", 131],
        ["Gloria in excelsis", 132],
        ["Dominus vobiscum", 133],
        ["Oraison", 134],
        ["L’Epistre", 134],
        ["Pourquoi on change le livre de droit à gauche", 135],
        ["Le Graduel", 137],
        ["L’Evangile", 138],
        ["Le Credo", 139],
        ["Dominus vobiscum", 139],
        ["L’Offrande", 139],
        ["L’Oblation", 141],
        ["Le vin & l’eau", 143],
        ["Le lavement des mains", 144],
        ["Orate fratres", 145],
        ["La Preface", 146],
        ["Le Canon", 149],
        ["Te igitur, &c.", 149],
        ["Le premier Memento", 151],
        ["Hanc igitur oblationem", 152],
        ["La Consecration & l’Elevation", 153],
        ["Unde & memores, &c.", 154],
        ["Supra qua", 156],
        ["Supplices te rogamus", 157],
        ["Le second Memento", 157],
        ["Per quem hæc omnia", 158],
        ["Per ipsum & cum ipso &c.", 160],
        ["Le Pater", 161],
        ["Libera nos", 163],
        ["Fraction de l’Hostie", 164],
        ["L’Agnus Dei", 165],
        ["La Paix", 165],
        ["La Communion", 166],
        ["Pourquoi on rapporte le livre du costé droit", 168],
        ["La benediction, & l’Evangile de saint Jean", 169]
    ]
}